root_tomography/__init__.py
root_tomography/bound.py
root_tomography/entity.py
root_tomography/estimator.py
root_tomography/experiment.py
root_tomography/gchi2.py
root_tomography/meas_statistics.py
root_tomography/optimizer.py
root_tomography/tools.py
root_tomography-0.7.dist-info/LICENSE
root_tomography-0.7.dist-info/METADATA
root_tomography-0.7.dist-info/WHEEL
root_tomography-0.7.dist-info/top_level.txt
root_tomography-0.7.dist-info/RECORD
