Metadata-Version: 2.1
Name: root-tomography
Version: 0.7
Summary: Python library for the root approach quantum tomography
Home-page: https://github.com/PQCLab/pyRootTomography
Author: Boris Bantysh
Author-email: bbantysh60000@gmail.com
Classifier: Programming Language :: Python :: 3
Classifier: License :: OSI Approved :: GNU General Public License v3 (GPLv3)
Classifier: Operating System :: OS Independent
Requires-Python: >=3.7
License-File: LICENSE
Requires-Dist: numpy (>=1.20.2)
Requires-Dist: scipy (>=1.6.2)
